Metadata-Version: 2.1
Name: steam-interfaces
Version: 0.2.6
Summary: Python library for working with the Steam API.
Home-page: https://github.com/Weebp-Team/steamapi
Download-URL: https://github.com/Weebp-Team/steamapi/archive/main.zip
Author: Tarodictrl
Author-email: vudi600@gmail.com
License: MIT License, see LICENSE file
Classifier: License :: OSI Approved :: MIT License
Classifier: Operating System :: OS Independent
Classifier: Intended Audience :: End Users/Desktop
Classifier: Intended Audience :: Developers
Classifier: Programming Language :: Python
Classifier: Programming Language :: Python :: 3
Classifier: Programming Language :: Python :: 3.6
Classifier: Programming Language :: Python :: 3.7
Classifier: Programming Language :: Python :: 3.8
Classifier: Programming Language :: Python :: Implementation :: PyPy
Classifier: Programming Language :: Python :: Implementation :: CPython
License-File: LICENSE
